django_aws_iot/__init__.py
django_aws_iot/aws_iot.py
django_aws_iot-1.1.0.dist-info/LICENSE
django_aws_iot-1.1.0.dist-info/METADATA
django_aws_iot-1.1.0.dist-info/WHEEL
django_aws_iot-1.1.0.dist-info/top_level.txt
django_aws_iot-1.1.0.dist-info/RECORD
