Metadata-Version: 2.1
Name: django-aws-iot
Version: 1.1.0
Summary: A django module that allows to connect and publish messages to AWS IoT
Home-page: https://github.com/anexia/django-aws-iot
Author: Harald Nezbeda
Author-email: hnezbeda@anexia-it.com
License: MIT License
Classifier: Development Status :: 5 - Production/Stable
Classifier: Framework :: Django
Classifier: Framework :: Django :: 3.2
Classifier: Framework :: Django :: 4.0
Classifier: Framework :: Django :: 4.1
Classifier: Intended Audience :: Developers
Classifier: License :: OSI Approved :: MIT License
Classifier: Operating System :: OS Independent
Classifier: Programming Language :: Python
Classifier: Programming Language :: Python :: 3
Classifier: Programming Language :: Python :: 3.7
Classifier: Programming Language :: Python :: 3.8
Classifier: Programming Language :: Python :: 3.9
Classifier: Programming Language :: Python :: 3.10
License-File: LICENSE
Requires-Dist: awsiotsdk
Requires-Dist: django
